spsdk_pqc/__init__.py
spsdk_pqc/__main__.py
spsdk_pqc/errors.py
spsdk_pqc/liboqs.so
spsdk_pqc/liboqs.so.0.12.0
spsdk_pqc/liboqs.so.7
spsdk_pqc/liboqs_oqs.py
spsdk_pqc/pqc_asn.py
spsdk_pqc/utils.py
spsdk_pqc/wrapper.py
spsdk_pqc/__pyinstaller/__init__.py
spsdk_pqc/__pyinstaller/hook-spsdk_pqc.py
spsdk_pqc-0.6.8.dist-info/METADATA
spsdk_pqc-0.6.8.dist-info/WHEEL
spsdk_pqc-0.6.8.dist-info/entry_points.txt
spsdk_pqc-0.6.8.dist-info/top_level.txt
spsdk_pqc-0.6.8.dist-info/RECORD
spsdk_pqc-0.6.8.dist-info/licenses/LICENSE
