Metadata-Version: 2.4
Name: spsdk-pqc
Version: 0.6.8
Summary: Post-Quantum Crypto support for SPSDK
Author: NXP
Maintainer-email: NXP <spsdk@nxp.com>
License-Expression: BSD-3-Clause
Project-URL: Homepage, https://github.com/nxp-mcuxpresso/spsdk_plugins/tree/master/pqc
Project-URL: Issues, https://github.com/nxp-mcuxpresso/spsdk_plugins/issues
Keywords: NXP,SPSDK,PQC,Dilithium,ML-DSA
Classifier: Development Status :: 2 - Pre-Alpha
Classifier: Intended Audience :: Developers
Classifier: Natural Language :: English
Classifier: Programming Language :: Python :: 3
Classifier: Programming Language :: Python :: 3.9
Classifier: Programming Language :: Python :: 3.10
Classifier: Programming Language :: Python :: 3.11
Classifier: Programming Language :: Python :: 3.12
Requires-Python: >=3.9
License-File: LICENSE
Requires-Dist: pyasn1
Requires-Dist: typing_extensions
Requires-Dist: click
Requires-Dist: pycryptodome
Dynamic: license-file
